AgentSmith/Agents.py
AgentSmith/utils.py
Agent_Smith-0.1.1.dist-info/LICENSE.txt
Agent_Smith-0.1.1.dist-info/METADATA
Agent_Smith-0.1.1.dist-info/WHEEL
Agent_Smith-0.1.1.dist-info/top_level.txt
Agent_Smith-0.1.1.dist-info/RECORD
